multigifview/__init__.py
multigifview/__main__.py
multigifview/core.py
multigifview/mainwindow.py
multigifview-0.2.9.data/data/man/man1/multigifview.1
multigifview-0.2.9.dist-info/LICENCE
multigifview-0.2.9.dist-info/METADATA
multigifview-0.2.9.dist-info/WHEEL
multigifview-0.2.9.dist-info/entry_points.txt
multigifview-0.2.9.dist-info/top_level.txt
multigifview-0.2.9.dist-info/RECORD
