Metadata-Version: 2.1
Name: multigifview
Version: 0.2.9
Summary: View multiple gif files
Home-page: https://github.com/johnomotani/multigifview
Author: John Omotani
Author-email: john.omotani@ukaea.uk
License: GPLv3+
Classifier: License :: OSI Approved :: GNU General Public License v3 or later (GPLv3+)
Classifier: Natural Language :: English
Classifier: Programming Language :: Python :: 3.6
Classifier: Programming Language :: Python :: 3.7
Classifier: Programming Language :: Python :: 3.8
License-File: LICENCE
Requires-Dist: pyqt5
Requires-Dist: qt.py
Requires-Dist: importlib-metadata ; python_version < "3.8"
